fsm_assignments/problem3_vending/vending_mealy.v
module vending_mealy(
    input wire clk,
    input wire rst,        
    input wire [1:0] coin, 
    output reg dispense,   
    output reg chg5        
);

    
    reg [1:0] state; 
    
    
    always @(posedge clk) begin
        if (rst) 
            state <= 2'b00;
        else case (state)
            2'b00: if (coin==2'b01) state <= 2'b01;      
                   else if (coin==2'b10) state <= 2'b10; 
            
            2'b01: if (coin==2'b01) state <= 2'b10;      
                   else if (coin==2'b10) state <= 2'b11; 
            
            2'b10: if (coin==2'b01) state <= 2'b11;      
                   else if (coin==2'b10) state <= 2'b00; 
            
            2'b11: if (coin==2'b01) state <= 2'b00;      
                   else if (coin==2'b10) state <= 2'b00; 
        endcase
    end
    
    
    always @(*) begin
        dispense = 0;
        chg5 = 0;
        
        case (state)
            2'b10: if (coin==2'b10) dispense = 1;        
            2'b11: if (coin==2'b01) dispense = 1;        
                   else if (coin==2'b10) begin
                       dispense = 1;                      
                       chg5 = 1;                          
                   end
        endcase
    end

endmodule

fsm_assignments/problem3_vending/tb_vending_mealy.v
module tb_vending_mealy;
    reg clk, rst;
    reg [1:0] coin;
    wire dispense, chg5;
    
    vending_mealy dut(.clk(clk), .rst(rst), .coin(coin), 
                      .dispense(dispense), .chg5(chg5));
    
   
    always #5 clk = ~clk;
    
    task put5; 
        begin 
            @(posedge clk); coin=2'b01; 
            @(posedge clk); coin=2'b00; 
        end 
    endtask
    
    task put10; 
        begin 
            @(posedge clk); coin=2'b10; 
            @(posedge clk); coin=2'b00; 
        end 
    endtask
    
    initial begin
        
        $dumpfile("vending.vcd");
        $dumpvars(0, tb_vending_mealy);

        clk=0; rst=1; coin=0;
        #10 rst=0;
        
       
        put10; put10; 
        #10;
        
        
        rst=1; #10 rst=0;
        
        
        put5; put10; put10;
        #10;
        
        $finish;
    end
    
    initial $monitor("t=%0t state=%0d coin=%0d disp=%b chg5=%b", 
                     $time, dut.state, coin, dispense, chg5);
endmodule

fsm_assignments/problem3_vending/vending.vcd
$date
	Sat Aug 23 18:25:46 2025
$end
$version
	Icarus Verilog
$end
$timescale
	1s
$end
$scope module tb_vending_mealy $end
$var wire 1 ! dispense $end
$var wire 1 " chg5 $end
$var reg 1 # clk $end
$var reg 2 $ coin [1:0] $end
$var reg 1 % rst $end
$scope module dut $end
$var wire 1 # clk $end
$var wire 2 & coin [1:0] $end
$var wire 1 % rst $end
$var reg 1 " chg5 $end
$var reg 1 ! dispense $end
$var reg 2 ' state [1:0] $end
$upscope $end
$scope task put10 $end
$upscope $end
$scope task put5 $end
$upscope $end
$upscope $end
$enddefinitions $end
$comment Show the parameter values. $end
$dumpall
$end
#0
$dumpvars
bx '
b0 &
1%
b0 $
0#
0"
0!
$end
#5
b0 '
1#
#10
0#
0%
#15
1!
b10 '
b10 $
b10 &
1#
#20
0#
#25
b0 '
0!
b0 $
b0 &
1#
#30
0#
#35
1!
b10 '
b10 $
b10 &
1#
#40
0#
#45
b0 '
0!
b0 $
b0 &
1#
#50
0#
#55
1#
1%
#60
0#
#65
b1 '
b1 $
b1 &
1#
0%
#70
0#
#75
b10 '
b0 $
b0 &
1#
#80
0#
#85
b0 '
0!
b10 $
b10 &
1#
#90
0#
#95
b10 '
b0 $
b0 &
1#
#100
0#
#105
b0 '
0!
b10 $
b10 &
1#
#110
0#
#115
b10 '
b0 $
b0 &
1#
