LAB 1/bit4_equality/b4_equal.v
module b4_equal(input [3:0] A, B,
                output eq);

                assign eq = &(~(A - B));
endmodule

LAB 1/bit4_equality/b4_equal_tb.v
`timescale 1ns/1ns

module b4_equal_tb;
                reg [3:0] A, B;
                wire eq;

            b4_equal equal1(.A(A),
                            .B(B),
                            .eq(eq)
            );


            initial begin
                $dumpfile("b4_equal_tb.vcd");
                $dumpvars(0,b4_equal_tb);

                $display("Checking Equality Wait.....");

                A = 0000;   B = 0000;   #10;
                A = 0000;   B = 0001;   #10;
                A = 0101;   B = 1010;   #10;
                A = 1001;   B = 1001;   #10;
                A = 1011;   B = 1000;   #10;
                A = 1110;   B = 1110;   #10;
                A = 1111;   B = 1000;   #10;
                A = 1111;   B = 1111;   #10;
                A = 1000;   B = 0000;   #10;

                $display(" Program Complete....");

                $finish;
            end


endmodule

LAB 1/bit4_equality/b4_equal_tb.vcd
$date
	Thu Jul 31 00:30:40 2025
$end
$version
	Icarus Verilog
$end
$timescale
	1ns
$end
$scope module b4_equal_tb $end
$var wire 1 ! eq $end
$var reg 4 " A [3:0] $end
$var reg 4 # B [3:0] $end
$scope module equal1 $end
$var wire 4 $ A [3:0] $end
$var wire 4 % B [3:0] $end
$var wire 1 ! eq $end
$upscope $end
$upscope $end
$enddefinitions $end
$comment Show the parameter values. $end
$dumpall
$end
#0
$dumpvars
b0 %
b0 $
b0 #
b0 "
1!
$end
#10
0!
b1 #
b1 %
#20
b10 #
b10 %
b101 "
b101 $
#30
1!
b1001 #
b1001 %
b1001 "
b1001 $
#40
0!
b1000 #
b1000 %
b11 "
b11 $
#50
1!
b110 #
b110 %
b110 "
b110 $
#60
0!
b1000 #
b1000 %
b111 "
b111 $
#70
1!
b111 #
b111 %
#80
0!
b0 #
b0 %
b1000 "
b1000 $
