fsm_assignments/problem1_seqdet/seq_detect_mealy.v
module seq_detect_mealy(input clk,
                        input rst,
                        input din,
                        output y);
    
    reg [1:0] present_state, next_state;
    
    parameter S0 = 2'b00;
    parameter S1 = 2'b01;
    parameter S2 = 2'b10;
    parameter S3 = 2'b11;

    // state register
    always @ (posedge clk, posedge rst)
        begin
            if(rst) present_state <= S0;
            else    present_state <= next_state;
        end
    // next state logic
    always @ (*)
        case (present_state)
            S0: if(din)  
                        next_state = S1;
                else      
                        next_state = S0;

            S1: if(din)  
                        next_state = S2;
                else      
                        next_state = S0;

            S2: if(din)  
                        next_state = S2;
                    else      
                        next_state = S3;

            S3: if(din) 
                        next_state = S1;
                else 
                        next_state = S0;

            default:    next_state = S0;

        endcase

        assign y = (present_state == S3) && din;

endmodule

fsm_assignments/problem1_seqdet/seq_detect_mealy_tb.v

module seq_detect_mealy_tb;
                    reg clk;
                    reg rst; 
                    reg din;
                    wire y;

        seq_detect_mealy duc(.clk(clk), .rst(rst), .din(din), .y(y));

        initial clk = 0;
        always #5 clk = ~clk;

        initial begin
            $dumpfile("seq_detect_mealy_tb.vcd");
            $dumpvars(0,seq_detect_mealy_tb);
            
            $display(" Starting Testing ");

            $display("Time\tclk\trst\tdin\ty");
            $monitor("%0t\t%b\t%b\t%b\t%b", $time, clk, rst, din, y);

            rst = 1;
            din = 0;
            @(posedge clk);
            @(posedge clk);

            rst = 0;

            // input test
           @(posedge clk) din = 1;
           @(posedge clk) din = 1;
           @(posedge clk) din = 0;
           @(posedge clk) din = 1;

           @(posedge clk) din = 0;

            // overlapping input test stream 
           @(posedge clk) din = 0; 
           @(posedge clk) din = 1;  // 1
           @(posedge clk) din = 1; // 1
           @(posedge clk) din = 0; // 0
           @(posedge clk) din = 1; // 1 -> detect
           @(posedge clk) din = 1; // overlap
           @(posedge clk) din = 0; 
           @(posedge clk) din = 1; // detect again
            
            
            #20 
            $display(" Simulation finished... ");
            $finish;
        end
endmodule

fsm_assignments/problem1_seqdet/seq_detect_mealy_tb.vcd
$date
	Thu Aug 21 00:50:56 2025
$end
$version
	Icarus Verilog
$end
$timescale
	1s
$end
$scope module seq_detect_mealy_tb $end
$var wire 1 ! y $end
$var reg 1 " clk $end
$var reg 1 # din $end
$var reg 1 $ rst $end
$scope module duc $end
$var wire 1 " clk $end
$var wire 1 # din $end
$var wire 1 $ rst $end
$var wire 1 ! y $end
$var parameter 2 % S0 $end
$var parameter 2 & S1 $end
$var parameter 2 ' S2 $end
$var parameter 2 ( S3 $end
$var reg 2 ) next_state [1:0] $end
$var reg 2 * present_state [1:0] $end
$upscope $end
$upscope $end
$enddefinitions $end
$comment Show the parameter values. $end
$dumpall
b11 (
b10 '
b1 &
b0 %
$end
#0
$dumpvars
b0 *
b0 )
1$
0#
0"
0!
$end
#5
1"
#10
0"
#15
0$
1"
#20
0"
#25
b1 )
1#
1"
#30
0"
#35
b10 )
b1 *
1"
#40
0"
#45
b10 *
b11 )
0#
1"
#50
0"
#55
1!
b11 *
b1 )
1#
1"
#60
0"
#65
b1 *
0!
b0 )
0#
1"
#70
0"
#75
b0 *
1"
#80
0"
#85
b1 )
1#
1"
#90
0"
#95
b10 )
b1 *
1"
#100
0"
#105
b10 *
b11 )
0#
1"
#110
0"
#115
1!
b11 *
b1 )
1#
1"
#120
0"
#125
b10 )
0!
b1 *
1"
#130
0"
#135
b10 *
b11 )
0#
1"
#140
0"
#145
1!
b11 *
b1 )
1#
1"
#150
0"
#155
b10 )
0!
b1 *
1"
#160
0"
#165
b10 *
1"
