fsm_assignments/problem4_link/slave_fsm.v
module slave_fsm(
    input wire clk,
    input wire rst,
    input wire req,
    input wire [7:0] data_in,
    output reg ack,
    output reg [7:0] last_byte
);

    
    localparam WAIT_REQ   = 2'b00;
    localparam ASSERT_ACK = 2'b01;
    localparam HOLD_ACK   = 2'b10;
    localparam DROP_ACK   = 2'b11;
    
    reg [1:0] state, next_state;
    
    
    always @(posedge clk) begin
        if (rst) begin
            state <= WAIT_REQ;
        end else begin
            state <= next_state;
        end
    end
    
   
    always @(*) begin
        case (state)
            WAIT_REQ: begin
                if (req) begin
                    next_state = ASSERT_ACK;
                end else begin
                    next_state = WAIT_REQ;
                end
            end
            
            ASSERT_ACK: begin
                next_state = HOLD_ACK;
            end
            
            HOLD_ACK: begin
                next_state = DROP_ACK;
            end
            
            DROP_ACK: begin
                if (!req) begin
                    next_state = WAIT_REQ;
                end else begin
                    next_state = DROP_ACK;
                end
            end
        endcase
    end
    
   
    always @(posedge clk) begin
        if (rst) begin
            ack <= 1'b0;
            last_byte <= 8'h00;
        end else begin
            
            ack <= (state == ASSERT_ACK) || (state == HOLD_ACK);
            
            
            if (req && state == WAIT_REQ) begin
                last_byte <= data_in;
            end
        end
    end

endmodule

fsm_assignments/problem4_link/master_fsm.v
module master_fsm(
    input wire clk,
    input wire rst,
    input wire ack,
    output reg req,
    output reg [7:0] data,
    output reg done
);

    
    localparam IDLE       = 2'b00;
    localparam ASSERT_REQ = 2'b01;
    localparam WAIT_ACK   = 2'b10;
    localparam DROP_REQ   = 2'b11;
    
    
    reg [1:0] state, next_state;
    reg [1:0] byte_count, next_byte_count;
    
    
    reg [7:0] data_array [0:3];
    
    initial begin
        data_array[0] = 8'hA0;
        data_array[1] = 8'hA1;
        data_array[2] = 8'hA2;
        data_array[3] = 8'hA3;
    end
    
    
    always @(posedge clk) begin
        if (rst) begin
            state <= IDLE;
            byte_count <= 2'b00;
        end else begin
            state <= next_state;
            byte_count <= next_byte_count;
        end
    end
    
    
    always @(*) begin
        next_state = state;
        next_byte_count = byte_count;
        
        case (state)
            IDLE: begin
                if (byte_count < 4) begin
                    next_state = ASSERT_REQ;
                end
            end
            
            ASSERT_REQ: begin
                next_state = WAIT_ACK;
            end
            
            WAIT_ACK: begin
                if (ack) begin
                    next_state = DROP_REQ;
                end
            end
            
            DROP_REQ: begin
                if (!ack) begin
                    next_byte_count = byte_count + 1;
                    if (byte_count == 3) begin
                        next_state = IDLE; 
                    end else begin
                        next_state = IDLE; 
                    end
                end
            end
        endcase
    end
    
    
    always @(*) begin
        req = (state == ASSERT_REQ) || (state == WAIT_ACK);
        data = data_array[byte_count];
        done = (state == DROP_REQ) && (!ack) && (byte_count == 3);
    end

endmodule

fsm_assignments/problem4_link/link_top.v
module link_top(
    input wire clk,
    input wire rst,
    output wire done
);

    
    wire req;
    wire ack;
    wire [7:0] data;
    wire [7:0] last_byte;
    
    
    master_fsm master_inst (
        .clk(clk),
        .rst(rst),
        .ack(ack),
        .req(req),
        .data(data),
        .done(done)
    );
    
   
    slave_fsm slave_inst (
        .clk(clk),
        .rst(rst),
        .req(req),
        .data_in(data),
        .ack(ack),
        .last_byte(last_byte)
    );

endmodule

fsm_assignments/problem4_link/tb_link_top.v
module tb_link_top;

    reg clk, rst;
    wire done;
    
    link_top dut(.clk(clk), .rst(rst), .done(done));
    
    
    initial begin
        clk = 0;
        forever #10 clk = ~clk;
    end
    
   
    initial begin
        $dumpfile("handshake.vcd");
        $dumpvars(0, tb_link_top);
        
        rst = 1;
        #25;
        rst = 0;
        
        
        wait(done == 1);
        #20;
        $finish;
    end

endmodule

fsm_assignments/problem4_link/handshake.vcd
$date
	Sat Aug 23 19:54:15 2025
$end
$version
	Icarus Verilog
$end
$timescale
	1s
$end
$scope module tb_link_top $end
$var wire 1 ! done $end
$var reg 1 " clk $end
$var reg 1 # rst $end
$scope module dut $end
$var wire 1 " clk $end
$var wire 1 # rst $end
$var wire 1 $ req $end
$var wire 8 % last_byte [7:0] $end
$var wire 1 ! done $end
$var wire 8 & data [7:0] $end
$var wire 1 ' ack $end
$scope module master_inst $end
$var wire 1 " clk $end
$var wire 1 # rst $end
$var wire 1 ' ack $end
$var parameter 2 ( ASSERT_REQ $end
$var parameter 2 ) DROP_REQ $end
$var parameter 2 * IDLE $end
$var parameter 2 + WAIT_ACK $end
$var reg 2 , byte_count [1:0] $end
$var reg 8 - data [7:0] $end
$var reg 1 ! done $end
$var reg 2 . next_byte_count [1:0] $end
$var reg 2 / next_state [1:0] $end
$var reg 1 $ req $end
$var reg 2 0 state [1:0] $end
$upscope $end
$scope module slave_inst $end
$var wire 1 " clk $end
$var wire 8 1 data_in [7:0] $end
$var wire 1 $ req $end
$var wire 1 # rst $end
$var parameter 2 2 ASSERT_ACK $end
$var parameter 2 3 DROP_ACK $end
$var parameter 2 4 HOLD_ACK $end
$var parameter 2 5 WAIT_REQ $end
$var reg 1 ' ack $end
$var reg 8 6 last_byte [7:0] $end
$var reg 2 7 next_state [1:0] $end
$var reg 2 8 state [1:0] $end
$upscope $end
$upscope $end
$upscope $end
$enddefinitions $end
$comment Show the parameter values. $end
$dumpall
b0 5
b10 4
b11 3
b1 2
b10 +
b0 *
b11 )
b1 (
$end
#0
$dumpvars
bx 8
bx 7
bx 6
bx 1
bx 0
bx /
bx .
bx -
bx ,
x'
bx &
bx %
x$
1#
0"
x!
$end
#10
b0 7
0!
b10100000 &
b10100000 -
b10100000 1
0$
b0 .
b1 /
b0 ,
b0 0
b0 8
b0 %
b0 6
0'
1"
#20
0"
#25
0#
#30
b1 7
1$
b10 /
b1 0
1"
#40
0"
#50
b10 7
b10 0
b1 8
b10100000 %
b10100000 6
1"
#60
0"
#70
b11 /
b11 7
1'
b10 8
1"
#80
0"
#90
b0 7
0$
b11 0
b11 8
1"
#100
0"
#110
b0 /
b1 .
0'
b0 8
1"
#120
0"
#130
b10100001 &
b10100001 -
b10100001 1
b1 /
b1 ,
b0 0
1"
#140
0"
#150
b1 7
1$
b10 /
b1 0
1"
#160
0"
#170
b10 7
b10 0
b1 8
b10100001 %
b10100001 6
1"
#180
0"
#190
b11 /
b11 7
1'
b10 8
1"
#200
0"
#210
b0 7
0$
b11 0
b11 8
1"
#220
0"
#230
b0 /
b10 .
0'
b0 8
1"
#240
0"
#250
b10100010 &
b10100010 -
b10100010 1
b1 /
b10 ,
b0 0
1"
#260
0"
#270
b1 7
1$
b10 /
b1 0
1"
#280
0"
#290
b10 7
b10 0
b1 8
b10100010 %
b10100010 6
1"
#300
0"
#310
b11 /
b11 7
1'
b10 8
1"
#320
0"
#330
b0 7
0$
b11 0
b11 8
1"
#340
0"
#350
b0 /
b11 .
0'
b0 8
1"
#360
0"
#370
b10100011 &
b10100011 -
b10100011 1
b1 /
b11 ,
b0 0
1"
#380
0"
#390
b1 7
1$
b10 /
b1 0
1"
#400
0"
#410
b10 7
b10 0
b1 8
b10100011 %
b10100011 6
1"
#420
0"
#430
b11 /
b11 7
1'
b10 8
1"
#440
0"
#450
b0 7
0$
b11 0
b11 8
1"
#460
0"
#470
1!
b0 /
b0 .
0'
b0 8
1"
#480
0"
#490
0!
b10100000 &
b10100000 -
b10100000 1
b1 /
b0 ,
b0 0
1"
